odoo/addons/portal_sale_personal_data_only/README.rst
odoo/addons/portal_sale_personal_data_only/__init__.py
odoo/addons/portal_sale_personal_data_only/__manifest__.py
odoo/addons/portal_sale_personal_data_only/hooks.py
odoo/addons/portal_sale_personal_data_only/i18n/de.po
odoo/addons/portal_sale_personal_data_only/i18n/es.po
odoo/addons/portal_sale_personal_data_only/i18n/it.po
odoo/addons/portal_sale_personal_data_only/i18n/portal_sale_personal_data_only.pot
odoo/addons/portal_sale_personal_data_only/i18n/zh_CN.po
odoo/addons/portal_sale_personal_data_only/readme/CONTRIBUTORS.rst
odoo/addons/portal_sale_personal_data_only/readme/DESCRIPTION.rst
odoo/addons/portal_sale_personal_data_only/readme/USAGE.rst
odoo/addons/portal_sale_personal_data_only/security/security.xml
odoo/addons/portal_sale_personal_data_only/static/description/icon.png
odoo/addons/portal_sale_personal_data_only/static/description/index.html
odoo/addons/portal_sale_personal_data_only/tests/__init__.py
odoo/addons/portal_sale_personal_data_only/tests/test_partner_access.py
odoo14_addon_portal_sale_personal_data_only-14.0.1.0.1.dev7.dist-info/METADATA
odoo14_addon_portal_sale_personal_data_only-14.0.1.0.1.dev7.dist-info/WHEEL
odoo14_addon_portal_sale_personal_data_only-14.0.1.0.1.dev7.dist-info/top_level.txt
odoo14_addon_portal_sale_personal_data_only-14.0.1.0.1.dev7.dist-info/RECORD
